drone-awe/Drone_test.py
drone-awe/PowerCorrection.py
drone-awe/__init__.py
drone-awe/app.py
drone-awe/app_old.py
drone-awe/classes.py
drone-awe/classes_test_weather.py
drone-awe/functions.py
drone-awe/functions_test.py
drone-awe/test_plotter.py
drone_awe/Drone_test.py
drone_awe/PowerCorrection.py
drone_awe/__init__.py
drone_awe/app.py
drone_awe/app_old.py
drone_awe/classes.py
drone_awe/classes_test_weather.py
drone_awe/conversions.py
drone_awe/drones.py
drone_awe/functions.py
drone_awe/functions_test.py
drone_awe/test_plotter.py
drone_awe/validationdata.py
drone_awe/validationdrones.py
drone_awe/validationsettings.py
drone_awe-1.0.1.dist-info/LICENSE
drone_awe-1.0.1.dist-info/METADATA
drone_awe-1.0.1.dist-info/WHEEL
drone_awe-1.0.1.dist-info/top_level.txt
drone_awe-1.0.1.dist-info/RECORD
