Metadata-Version: 2.1
Name: drone-awe
Version: 1.0.1
Summary: A versatile modeling package for drone performance in various weather environments.
Home-page: https://github.com/rymanderson/drone_awe
Author: Tyler Critchfield and Ryan Anderson
Author-email: rymanderson@gmail.com
License: UNKNOWN
Download-URL: https://github.com/rymanderson/drone_awe.git
Platform: UNKNOWN
Classifier: Programming Language :: Python :: 3
Classifier: License :: OSI Approved :: MIT License
Classifier: Operating System :: OS Independent
Requires-Dist: scipy
Requires-Dist: numpy
Requires-Dist: gekko
Requires-Dist: matplotlib
Requires-Dist: datetime
